Metadata-Version: 2.1
Name: xu2net
Version: 0.0.3
Summary: A python util package
Home-page: https://github.com/ThreeParty/U-2-Net.git
Author: cvdnn
Author-email: cvvdnn@gmail.com
License: UNKNOWN
Project-URL: Bug Tracker, https://github.com/ThreeParty/U-2-Net.git/issues
Keywords: pip,license
Platform: UNKNOWN
Classifier: Programming Language :: Python :: 3
Classifier: License :: OSI Approved :: MIT License
Classifier: Operating System :: OS Independent
Requires-Python: >=3.6
